sim/simple_memory.sv
`timescale 1ns/1ps

module simple_memory #(
    parameter MEM_WORDS = 2048
) (
    input  logic        clk,
    // Instruction port (read-only)
    input  logic [31:0] instr_addr,
    output logic [31:0] instr_rdata,
    // Data port (read/write)
    input  logic [31:0] data_addr,
    input  logic [31:0] data_wdata,
    input  logic [3:0]  data_we,
    input  logic        data_re,
    output logic [31:0] data_rdata
);

  logic [31:0] mem [0:MEM_WORDS-1];

  integer i;
  initial begin
    for (i = 0; i < MEM_WORDS; i = i + 1) begin
      mem[i] = 32'h0;
    end
  end

  // Provide a simple hook for testbench initialization
  task automatic load_hex(input string filename);
    $readmemh(filename, mem);
  endtask

  // Instruction fetch: combinational read
  assign instr_rdata = mem[instr_addr[31:2]];

  // Data read: combinational for this simple stage
  always_comb begin
    if (data_re) begin
      data_rdata = mem[data_addr[31:2]];
    end else begin
      data_rdata = 32'h0;
    end
  end

  // Data write
  always_ff @(posedge clk) begin
    if (|data_we) begin
      if (data_we[0]) mem[data_addr[31:2]][7:0]   <= data_wdata[7:0];
      if (data_we[1]) mem[data_addr[31:2]][15:8]  <= data_wdata[15:8];
      if (data_we[2]) mem[data_addr[31:2]][23:16] <= data_wdata[23:16];
      if (data_we[3]) mem[data_addr[31:2]][31:24] <= data_wdata[31:24];
    end
  end

endmodule

src/units/branch_unit.sv
`timescale 1ns/1ps

import rv32i_pkg::*;

module branch_unit (
    input  logic [31:0] rs1_val,
    input  logic [31:0] rs2_val,
    input  branch_t     branch_type,
    output logic        take_branch
);

  always_comb begin
    case (branch_type)
      BR_EQ:  take_branch = (rs1_val == rs2_val);
      BR_NE:  take_branch = (rs1_val != rs2_val);
      BR_LT:  take_branch = ($signed(rs1_val) < $signed(rs2_val));
      BR_GE:  take_branch = ($signed(rs1_val) >= $signed(rs2_val));
      BR_LTU: take_branch = (rs1_val < rs2_val);
      BR_GEU: take_branch = (rs1_val >= rs2_val);
      default: take_branch = 1'b0;
    endcase
  end

endmodule

src/units/alu.sv
`timescale 1ns/1ps

import rv32i_pkg::*;

module alu (
    input  logic [31:0] op_a,
    input  logic [31:0] op_b,
    input  alu_op_e     alu_op,
    output logic [31:0] result
);

  always_comb begin
    unique case (alu_op)
      ALU_ADD:  result = op_a + op_b;
      ALU_SUB:  result = op_a - op_b;
      ALU_SLL:  result = op_a << op_b[4:0];
      ALU_SLT:  result = ($signed(op_a) < $signed(op_b)) ? 32'd1 : 32'd0;
      ALU_SLTU: result = (op_a < op_b) ? 32'd1 : 32'd0;
      ALU_XOR:  result = op_a ^ op_b;
      ALU_SRL:  result = op_a >> op_b[4:0];
      ALU_SRA:  result = $signed(op_a) >>> op_b[4:0];
      ALU_OR:   result = op_a | op_b;
      ALU_AND:  result = op_a & op_b;
      default:  result = 32'h0;
    endcase
  end

endmodule

src/units/imm_gen.sv
`timescale 1ns/1ps

import rv32i_pkg::*;

module imm_gen (
    input  logic [31:0] instr,
    input  imm_t        imm_sel,
    output logic [31:0] imm
);

  always_comb begin
    case (imm_sel)
      IMM_I: imm = {{20{instr[31]}}, instr[31:20]};
      IMM_S: imm = {{20{instr[31]}}, instr[31:25], instr[11:7]};
      IMM_B: imm = {{19{instr[31]}}, instr[31], instr[7], instr[30:25], instr[11:8], 1'b0};
      IMM_U: imm = {instr[31:12], 12'h000};
      IMM_J: imm = {{11{instr[31]}}, instr[31], instr[19:12], instr[20], instr[30:21], 1'b0};
      IMM_Z: imm = {27'h0, instr[19:15]}; // zero-extend rs1 field (for shifts)
      default: imm = 32'h0;
    endcase
  end

endmodule

src/units/decoder.sv
`timescale 1ns/1ps

import rv32i_pkg::*;

module decoder (
    input  logic [31:0] instr,
    output control_t    ctrl,
    output logic [4:0]  rs1,
    output logic [4:0]  rs2,
    output logic [4:0]  rd
);

  logic [6:0] opcode;
  logic [2:0] funct3;
  logic [6:0] funct7;

  assign opcode = instr[6:0];
  assign funct3 = instr[14:12];
  assign funct7 = instr[31:25];
  assign rs1    = instr[19:15];
  assign rs2    = instr[24:20];
  assign rd     = instr[11:7];

  always_comb begin
    // Defaults implement NOP (addi x0, x0, 0)
    ctrl.imm_type    = IMM_I;
    ctrl.op1_sel     = OP1_RS1;
    ctrl.op2_sel     = OP2_IMM;
    ctrl.alu_op      = ALU_ADD;
    ctrl.branch_type = BR_EQ;
    ctrl.branch      = 1'b0;
    ctrl.jump        = 1'b0;
    ctrl.mem_read    = 1'b0;
    ctrl.mem_write   = 1'b0;
    ctrl.mem_funct3  = 3'b000;
    ctrl.reg_write   = 1'b0;
    ctrl.wb_sel      = WB_ALU;
    ctrl.is_lui      = 1'b0;
    ctrl.is_auipc    = 1'b0;

    unique case (opcode)
      7'b0110011: begin // R-type
        ctrl.op2_sel  = OP2_RS2;
        ctrl.reg_write = 1'b1;
        ctrl.wb_sel    = WB_ALU;
        unique case ({funct7, funct3})
          10'b0000000_000: ctrl.alu_op = ALU_ADD;
          10'b0100000_000: ctrl.alu_op = ALU_SUB;
          10'b0000000_001: ctrl.alu_op = ALU_SLL;
          10'b0000000_010: ctrl.alu_op = ALU_SLT;
          10'b0000000_011: ctrl.alu_op = ALU_SLTU;
          10'b0000000_100: ctrl.alu_op = ALU_XOR;
          10'b0000000_101: ctrl.alu_op = ALU_SRL;
          10'b0100000_101: ctrl.alu_op = ALU_SRA;
          10'b0000000_110: ctrl.alu_op = ALU_OR;
          10'b0000000_111: ctrl.alu_op = ALU_AND;
          default: ctrl.alu_op = ALU_ADD;
        endcase
      end

      7'b0010011: begin // I-type ALU immediate
        ctrl.reg_write = 1'b1;
        ctrl.wb_sel    = WB_ALU;
        ctrl.op2_sel   = OP2_IMM;
        ctrl.imm_type  = IMM_I;
        unique case (funct3)
          3'b000: ctrl.alu_op = ALU_ADD;                  // ADDI
          3'b010: ctrl.alu_op = ALU_SLT;                  // SLTI
          3'b011: ctrl.alu_op = ALU_SLTU;                 // SLTIU
          3'b100: ctrl.alu_op = ALU_XOR;                  // XORI
          3'b110: ctrl.alu_op = ALU_OR;                   // ORI
          3'b111: ctrl.alu_op = ALU_AND;                  // ANDI
          3'b001: begin // SLLI
            ctrl.alu_op  = ALU_SLL;
            ctrl.imm_type = IMM_Z;
          end
          3'b101: begin // SRLI/SRAI
            ctrl.imm_type = IMM_Z;
            ctrl.alu_op   = (funct7[5]) ? ALU_SRA : ALU_SRL;
          end
          default: ctrl.alu_op = ALU_ADD;
        endcase
      end

      7'b0000011: begin // Loads
        ctrl.reg_write = 1'b1;
        ctrl.mem_read  = 1'b1;
        ctrl.wb_sel    = WB_MEM;
        ctrl.op2_sel   = OP2_IMM;
        ctrl.imm_type  = IMM_I;
        ctrl.alu_op    = ALU_ADD; // address calc
        ctrl.mem_funct3 = funct3;
      end

      7'b0100011: begin // Stores
        ctrl.mem_write = 1'b1;
        ctrl.op2_sel   = OP2_IMM;
        ctrl.imm_type  = IMM_S;
        ctrl.alu_op    = ALU_ADD;
        ctrl.mem_funct3 = funct3;
      end

      7'b1100011: begin // Branches
        ctrl.branch    = 1'b1;
        ctrl.op2_sel   = OP2_RS2;
        ctrl.imm_type  = IMM_B;
        ctrl.alu_op    = ALU_ADD; // unused
        unique case (funct3)
          3'b000: ctrl.branch_type = BR_EQ;
          3'b001: ctrl.branch_type = BR_NE;
          3'b100: ctrl.branch_type = BR_LT;
          3'b101: ctrl.branch_type = BR_GE;
          3'b110: ctrl.branch_type = BR_LTU;
          3'b111: ctrl.branch_type = BR_GEU;
          default: ctrl.branch_type = BR_EQ;
        endcase
      end

      7'b1101111: begin // JAL
        ctrl.jump       = 1'b1;
        ctrl.reg_write  = 1'b1;
        ctrl.imm_type   = IMM_J;
        ctrl.wb_sel     = WB_PC4;
        ctrl.op1_sel    = OP1_PC;
        ctrl.op2_sel    = OP2_IMM;
        ctrl.alu_op     = ALU_ADD;
      end

      7'b1100111: begin // JALR
        ctrl.jump       = 1'b1;
        ctrl.reg_write  = 1'b1;
        ctrl.imm_type   = IMM_I;
        ctrl.wb_sel     = WB_PC4;
        ctrl.op1_sel    = OP1_RS1;
        ctrl.op2_sel    = OP2_IMM;
        ctrl.alu_op     = ALU_ADD;
      end

      7'b0110111: begin // LUI
        ctrl.reg_write = 1'b1;
        ctrl.imm_type  = IMM_U;
        ctrl.wb_sel    = WB_IMM;
        ctrl.op1_sel   = OP1_ZERO;
        ctrl.op2_sel   = OP2_IMM;
        ctrl.is_lui    = 1'b1;
        ctrl.alu_op    = ALU_ADD;
      end

      7'b0010111: begin // AUIPC
        ctrl.reg_write = 1'b1;
        ctrl.imm_type  = IMM_U;
        ctrl.wb_sel    = WB_ALU;
        ctrl.op1_sel   = OP1_PC;
        ctrl.op2_sel   = OP2_IMM;
        ctrl.is_auipc  = 1'b1;
        ctrl.alu_op    = ALU_ADD;
      end

      default: begin
        // keep NOP defaults
      end
    endcase
  end

endmodule

src/units/regfile.sv
`timescale 1ns/1ps

module regfile (
    input  logic        clk,
    input  logic        rst,
    input  logic        we,
    input  logic [4:0]  waddr,
    input  logic [31:0] wdata,
    input  logic [4:0]  raddr1,
    input  logic [4:0]  raddr2,
    output logic [31:0] rdata1,
    output logic [31:0] rdata2
);

  logic [31:0] regs[31:0];

  integer i;
  always_ff @(posedge clk or posedge rst) begin
    if (rst) begin
      for (i = 0; i < 32; i = i + 1) begin
        regs[i] <= 32'h0;
      end
    end else if (we && (waddr != 5'd0)) begin
      regs[waddr] <= wdata;
    end
  end

  assign rdata1 = (raddr1 == 5'd0) ? 32'h0 : regs[raddr1];
  assign rdata2 = (raddr2 == 5'd0) ? 32'h0 : regs[raddr2];

endmodule

src/core/rv32i_cpu.sv
`timescale 1ns/1ps

import rv32i_pkg::*;

module rv32i_cpu (
    input  logic        clk,
    input  logic        rst,
    // Instruction memory interface
    output logic [31:0] instr_addr,
    input  logic [31:0] instr_rdata,
    // Data memory interface
    output logic [31:0] data_addr,
    output logic [31:0] data_wdata,
    output logic [3:0]  data_we,
    output logic        data_re,
    input  logic [31:0] data_rdata,
    // Debug/trace visibility
    output logic [31:0] dbg_pc_f,
    output logic [31:0] dbg_instr_f,
    output logic [31:0] dbg_instr_d,
    output logic [31:0] dbg_instr_e,
    output logic [31:0] dbg_result_e,
    output logic        dbg_branch_taken
);

  localparam logic [31:0] NOP = 32'h00000013; // addi x0, x0, 0

  // Fetch stage
  logic [31:0] pc_f;
  logic [31:0] pc_next;
  logic [31:0] pc_plus4_f;
  logic [31:0] instr_f;

  assign instr_addr = pc_f;
  assign instr_f    = instr_rdata;
  assign pc_plus4_f = pc_f + 32'd4;

  // Fetch/Decode pipeline registers
  logic [31:0] fd_pc;
  logic [31:0] fd_instr;

  // Decode stage signals
  control_t ctrl_d;
  logic [4:0] rs1_d, rs2_d, rd_d;
  logic [31:0] imm_d;
  logic [31:0] rs1_val_d, rs2_val_d;

  // Decode/Execute pipeline registers
  logic [31:0] de_pc;
  logic [31:0] de_instr;
  control_t de_ctrl;
  logic [4:0] de_rs1, de_rs2, de_rd;
  logic [31:0] de_rs1_val, de_rs2_val;
  logic [31:0] de_imm;

  // Execute stage helpers
  logic [31:0] op1_e, op2_e;
  logic [31:0] alu_result_e;
  logic [31:0] branch_target_e;
  logic branch_cond_e;
  logic branch_taken_e;
  logic [31:0] load_data_e;
  logic [31:0] wb_data_e;

  // Register file instance
  regfile u_regfile (
      .clk    (clk),
      .rst    (rst),
      .we     (de_ctrl.reg_write),
      .waddr  (de_rd),
      .wdata  (wb_data_e),
      .raddr1 (rs1_d),
      .raddr2 (rs2_d),
      .rdata1 (rs1_val_d),
      .rdata2 (rs2_val_d)
  );

  decoder u_decoder (
      .instr (fd_instr),
      .ctrl  (ctrl_d),
      .rs1   (rs1_d),
      .rs2   (rs2_d),
      .rd    (rd_d)
  );

  imm_gen u_imm_gen (
      .instr  (fd_instr),
      .imm_sel(ctrl_d.imm_type),
      .imm    (imm_d)
  );

  alu u_alu (
      .op_a  (op1_e),
      .op_b  (op2_e),
      .alu_op(de_ctrl.alu_op),
      .result(alu_result_e)
  );

  branch_unit u_branch_unit (
      .rs1_val    (de_rs1_val),
      .rs2_val    (de_rs2_val),
      .branch_type(de_ctrl.branch_type),
      .take_branch(branch_cond_e)
  );

  // FETCH stage registers
  always_ff @(posedge clk or posedge rst) begin
    if (rst) begin
      pc_f     <= 32'h0;
      fd_pc    <= 32'h0;
      fd_instr <= NOP;
    end else begin
      pc_f  <= pc_next;
      fd_pc <= pc_f;
      fd_instr <= branch_taken_e ? NOP : instr_f; // flush on branch
    end
  end

  // DECODE/EXECUTE pipeline registers
  always_ff @(posedge clk or posedge rst) begin
    if (rst) begin
      de_pc      <= 32'h0;
      de_instr   <= NOP;
      de_ctrl    <= '0;
      de_rs1     <= 5'd0;
      de_rs2     <= 5'd0;
      de_rd      <= 5'd0;
      de_rs1_val <= 32'h0;
      de_rs2_val <= 32'h0;
      de_imm     <= 32'h0;
    end else if (branch_taken_e) begin
      // Flush decode stage when a branch resolves taken in execute
      de_pc      <= 32'h0;
      de_instr   <= NOP;
      de_ctrl    <= '0;
      de_rs1     <= 5'd0;
      de_rs2     <= 5'd0;
      de_rd      <= 5'd0;
      de_rs1_val <= 32'h0;
      de_rs2_val <= 32'h0;
      de_imm     <= 32'h0;
    end else begin
      de_pc      <= fd_pc;
      de_instr   <= fd_instr;
      de_ctrl    <= ctrl_d;
      de_rs1     <= rs1_d;
      de_rs2     <= rs2_d;
      de_rd      <= rd_d;
      de_rs1_val <= rs1_val_d;
      de_rs2_val <= rs2_val_d;
      de_imm     <= imm_d;
    end
  end

  // Operand selection
  always_comb begin
    unique case (de_ctrl.op1_sel)
      OP1_RS1:  op1_e = de_rs1_val;
      OP1_PC:   op1_e = de_pc;
      OP1_ZERO: op1_e = 32'h0;
      default:  op1_e = de_rs1_val;
    endcase
  end

  always_comb begin
    op2_e = (de_ctrl.op2_sel == OP2_IMM) ? de_imm : de_rs2_val;
  end

  // Branch and jump handling
  always_comb begin
    if (de_ctrl.jump && (de_instr[6:0] == 7'b1100111)) begin
      // JALR target needs LSB cleared
      branch_target_e = (de_rs1_val + de_imm) & ~32'h1;
    end else begin
      branch_target_e = de_pc + de_imm;
    end
  end

  assign branch_taken_e = (de_ctrl.branch && branch_cond_e) || de_ctrl.jump;

  // Data memory interface (no stalling, single-cycle view)
  logic [31:0] addr_e;
  logic [3:0]  be_e;
  logic [31:0] wdata_e;

  assign addr_e = de_rs1_val + de_imm;

  always_comb begin
    // Default store parameters
    be_e    = 4'b0000;
    wdata_e = de_rs2_val;

    if (de_ctrl.mem_write) begin
      unique case (de_ctrl.mem_funct3)
        3'b000: begin // SB
          be_e    = 4'b0001 << addr_e[1:0];
          wdata_e = {4{de_rs2_val[7:0]}} << (8 * addr_e[1:0]);
        end
        3'b001: begin // SH
          be_e    = addr_e[1] ? 4'b1100 : 4'b0011;
          wdata_e = {2{de_rs2_val[15:0]}} << (16 * addr_e[1]);
        end
        default: begin // SW
          be_e    = 4'b1111;
          wdata_e = de_rs2_val;
        end
      endcase
    end
  end

  // Load data sign/zero extension
  always_comb begin
    load_data_e = data_rdata;
    unique case (de_ctrl.mem_funct3)
      3'b000: begin // LB
        logic [7:0] b;
        b = data_rdata >> (8 * addr_e[1:0]);
        load_data_e = {{24{b[7]}}, b};
      end
      3'b100: begin // LBU
        logic [7:0] b;
        b = data_rdata >> (8 * addr_e[1:0]);
        load_data_e = {24'h0, b};
      end
      3'b001: begin // LH
        logic [15:0] h;
        h = data_rdata >> (16 * addr_e[1]);
        load_data_e = {{16{h[15]}}, h};
      end
      3'b101: begin // LHU
        logic [15:0] h;
        h = data_rdata >> (16 * addr_e[1]);
        load_data_e = {16'h0, h};
      end
      default: load_data_e = data_rdata; // LW and default
    endcase
  end

  // Write-back selection
  always_comb begin
    unique case (de_ctrl.wb_sel)
      WB_MEM: wb_data_e = load_data_e;
      WB_PC4: wb_data_e = de_pc + 32'd4;
      WB_IMM: wb_data_e = de_imm;
      default: wb_data_e = alu_result_e;
    endcase
  end

  // Output assignments
  assign data_addr  = addr_e;
  assign data_wdata = wdata_e;
  assign data_we    = de_ctrl.mem_write ? be_e : 4'b0000;
  assign data_re    = de_ctrl.mem_read;

  assign pc_next = branch_taken_e ? branch_target_e : pc_plus4_f;

  // Debug/trace
  assign dbg_pc_f         = pc_f;
  assign dbg_instr_f      = instr_f;
  assign dbg_instr_d      = fd_instr;
  assign dbg_instr_e      = de_instr;
  assign dbg_result_e     = wb_data_e;
  assign dbg_branch_taken = branch_taken_e;

endmodule

sim/universal_tb.sv
`timescale 1ns/1ps

import rv32i_pkg::*;

module universal_tb;

  // Clock and reset
  logic clk = 0;
  logic rst = 1;

  // Memory interfaces
  logic [31:0] instr_addr;
  logic [31:0] instr_rdata;
  logic [31:0] data_addr;
  logic [31:0] data_wdata;
  logic [3:0]  data_we;
  logic        data_re;
  logic [31:0] data_rdata;

  // Simulation controls
  integer cycle_count = 0;
  integer max_cycles  = 200;
  string  hexfile     = "tests/sample_program.hex";

  integer trace_fd;

  // Clock generation: 10ns period
  always #5 clk = ~clk;

  // DUT instance
  rv32i_cpu dut (
      .clk            (clk),
      .rst            (rst),
      .instr_addr     (instr_addr),
      .instr_rdata    (instr_rdata),
      .data_addr      (data_addr),
      .data_wdata     (data_wdata),
      .data_we        (data_we),
      .data_re        (data_re),
      .data_rdata     (data_rdata),
      .dbg_pc_f       (),
      .dbg_instr_f    (),
      .dbg_instr_d    (),
      .dbg_instr_e    (),
      .dbg_result_e   (),
      .dbg_branch_taken()
  );

  // Simple unified memory
  simple_memory mem (
      .clk         (clk),
      .instr_addr  (instr_addr),
      .instr_rdata (instr_rdata),
      .data_addr   (data_addr),
      .data_wdata  (data_wdata),
      .data_we     (data_we),
      .data_re     (data_re),
      .data_rdata  (data_rdata)
  );

  // Optional plusargs for configuration
  initial begin
    if ($value$plusargs("HEX=%s", hexfile)) begin
      $display("Loading program from %s", hexfile);
    end else begin
      $display("Defaulting to program %s", hexfile);
    end

    if ($value$plusargs("MAX_CYCLES=%d", max_cycles)) begin
      $display("Max cycles set to %0d", max_cycles);
    end
  end

  // Initialize memory before releasing reset
  initial begin
    mem.load_hex(hexfile);
  end

  // Reset sequence
  initial begin
    rst = 1'b1;
    repeat (5) @(posedge clk);
    rst = 1'b0;
  end

  // Waveform dump
  initial begin
    $dumpfile("sim/out.vcd");
    $dumpvars(0, universal_tb);
  end

  // Trace logging
  initial begin
    trace_fd = $fopen("sim/pipeline_trace.log", "w");
    $fwrite(trace_fd, "cycle,pc_f,instr_fetch,instr_decode,instr_execute,result_execute,stall,branch_taken\n");
  end

  // Cycle-by-cycle tracing and stop conditions
  always_ff @(posedge clk) begin
    if (rst) begin
      cycle_count <= 0;
    end else begin
      cycle_count <= cycle_count + 1;
      $fwrite(trace_fd, "%0d,%08x,%08x,%08x,%08x,%08x,%s,%0d\n",
              cycle_count,
              dut.dbg_pc_f,
              dut.dbg_instr_f,
              dut.dbg_instr_d,
              dut.dbg_instr_e,
              dut.dbg_result_e,
              "none",
              dut.dbg_branch_taken);

      if (dut.dbg_instr_e == 32'h00100073 || dut.dbg_instr_e == 32'h00000073) begin
        $display("Halting on system instruction at cycle %0d", cycle_count);
        $finish;
      end

      if (cycle_count >= max_cycles) begin
        $display("Reached max cycles (%0d). Finishing simulation.", max_cycles);
        $finish;
      end
    end
  end

endmodule

sim/out.vcd
$date
	Mon Nov 17 20:54:18 2025
$end
$version
	Icarus Verilog
$end
$timescale
	1ps
$end
$scope module universal_tb $end
$var wire 32 ! instr_rdata [31:0] $end
$var wire 32 " instr_addr [31:0] $end
$var wire 4 # data_we [3:0] $end
$var wire 32 $ data_wdata [31:0] $end
$var wire 1 % data_re $end
$var wire 32 & data_rdata [31:0] $end
$var wire 32 ' data_addr [31:0] $end
$var reg 1 ( clk $end
$var reg 1 ) rst $end
$var integer 32 * cycle_count [31:0] $end
$var integer 32 + max_cycles [31:0] $end
$var integer 32 , trace_fd [31:0] $end
$scope module dut $end
$var wire 1 - branch_taken_e $end
$var wire 1 ( clk $end
$var wire 32 . data_addr [31:0] $end
$var wire 32 / data_wdata [31:0] $end
$var wire 1 0 dbg_branch_taken $end
$var wire 32 1 dbg_instr_d [31:0] $end
$var wire 32 2 dbg_instr_e [31:0] $end
$var wire 32 3 dbg_instr_f [31:0] $end
$var wire 32 4 dbg_pc_f [31:0] $end
$var wire 32 5 dbg_result_e [31:0] $end
$var wire 32 6 instr_addr [31:0] $end
$var wire 32 7 instr_f [31:0] $end
$var wire 1 ) rst $end
$var wire 32 8 rs2_val_d [31:0] $end
$var wire 5 9 rs2_d [4:0] $end
$var wire 32 : rs1_val_d [31:0] $end
$var wire 5 ; rs1_d [4:0] $end
$var wire 5 < rd_d [4:0] $end
$var wire 32 = pc_plus4_f [31:0] $end
$var wire 32 > pc_next [31:0] $end
$var wire 32 ? instr_rdata [31:0] $end
$var wire 32 @ imm_d [31:0] $end
$var wire 4 A data_we [3:0] $end
$var wire 1 % data_re $end
$var wire 32 B data_rdata [31:0] $end
$var wire 26 C ctrl_d [25:0] $end
$var wire 1 D branch_cond_e $end
$var wire 32 E alu_result_e [31:0] $end
$var wire 32 F addr_e [31:0] $end
$var parameter 32 G NOP $end
$var reg 4 H be_e [3:0] $end
$var reg 32 I branch_target_e [31:0] $end
$var reg 26 J de_ctrl [25:0] $end
$var reg 32 K de_imm [31:0] $end
$var reg 32 L de_instr [31:0] $end
$var reg 32 M de_pc [31:0] $end
$var reg 5 N de_rd [4:0] $end
$var reg 5 O de_rs1 [4:0] $end
$var reg 32 P de_rs1_val [31:0] $end
$var reg 5 Q de_rs2 [4:0] $end
$var reg 32 R de_rs2_val [31:0] $end
$var reg 32 S fd_instr [31:0] $end
$var reg 32 T fd_pc [31:0] $end
$var reg 32 U load_data_e [31:0] $end
$var reg 32 V op1_e [31:0] $end
$var reg 32 W op2_e [31:0] $end
$var reg 32 X pc_f [31:0] $end
$var reg 32 Y wb_data_e [31:0] $end
$var reg 32 Z wdata_e [31:0] $end
$scope module u_alu $end
$var wire 4 [ alu_op [3:0] $end
$var wire 32 \ op_a [31:0] $end
$var wire 32 ] op_b [31:0] $end
$var reg 32 ^ result [31:0] $end
$upscope $end
$scope module u_branch_unit $end
$var wire 3 _ branch_type [2:0] $end
$var wire 32 ` rs1_val [31:0] $end
$var wire 32 a rs2_val [31:0] $end
$var reg 1 D take_branch $end
$upscope $end
$scope module u_decoder $end
$var wire 32 b instr [31:0] $end
$var wire 5 c rs2 [4:0] $end
$var wire 5 d rs1 [4:0] $end
$var wire 5 e rd [4:0] $end
$var wire 7 f opcode [6:0] $end
$var wire 7 g funct7 [6:0] $end
$var wire 3 h funct3 [2:0] $end
$var reg 26 i ctrl [25:0] $end
$upscope $end
$scope module u_imm_gen $end
$var wire 3 j imm_sel [2:0] $end
$var wire 32 k instr [31:0] $end
$var reg 32 l imm [31:0] $end
$upscope $end
$scope module u_regfile $end
$var wire 1 ( clk $end
$var wire 5 m raddr1 [4:0] $end
$var wire 5 n raddr2 [4:0] $end
$var wire 1 ) rst $end
$var wire 5 o waddr [4:0] $end
$var wire 32 p wdata [31:0] $end
$var wire 1 q we $end
$var wire 32 r rdata2 [31:0] $end
$var wire 32 s rdata1 [31:0] $end
$var integer 32 t i [31:0] $end
$upscope $end
$scope begin $unm_blk_39 $end
$var reg 8 u b [7:0] $end
$upscope $end
$scope begin $unm_blk_40 $end
$var reg 8 v b [7:0] $end
$upscope $end
$scope begin $unm_blk_41 $end
$var reg 16 w h [15:0] $end
$upscope $end
$scope begin $unm_blk_42 $end
$var reg 16 x h [15:0] $end
$upscope $end
$upscope $end
$scope module mem $end
$var wire 1 ( clk $end
$var wire 32 y data_addr [31:0] $end
$var wire 1 % data_re $end
$var wire 32 z data_wdata [31:0] $end
$var wire 4 { data_we [3:0] $end
$var wire 32 | instr_addr [31:0] $end
$var wire 32 } instr_rdata [31:0] $end
$var parameter 32 ~ MEM_WORDS $end
$var reg 32 !" data_rdata [31:0] $end
$var integer 32 "" i [31:0] $end
$scope task load_hex $end
$upscope $end
$upscope $end
$upscope $end
$enddefinitions $end
$comment Show the parameter values. $end
$dumpall
b100000000000 ~
b10011 G
$end
#0
$dumpvars
b100000000000 ""
b0 !"
bx }
bx |
b0 {
bx z
bx y
bx x
bx w
bx v
bx u
bx t
bx s
bx r
xq
b0 p
bx o
bx n
bx m
bx l
bx k
b0 j
b10000000000000000000 i
bx h
bx g
bx f
bx e
bx d
bx c
bx b
bx a
bx `
bx _
b0 ^
bx ]
bx \
bx [
bx Z
b0 Y
bx X
bx W
bx V
b0 U
bx T
bx S
bx R
bx Q
bx P
bx O
bx N
bx M
bx L
bx K
bx J
bx I
b0 H
bx F
b0 E
0D
b10000000000000000000 C
b0 B
b0 A
bx @
bx ?
bx >
bx =
bx <
bx ;
bx :
bx 9
bx 8
bx 7
bx 6
b0 5
bx 4
bx 3
bx 2
bx 1
x0
bx /
bx .
x-
b10000000000000000000000000000011 ,
b11001000 +
b0 *
1)
0(
bx '
b0 &
x%
bx $
b0 #
bx "
bx !
$end
#5000
b10000000000000010000 C
b10000000000000010000 i
b0 :
b0 s
b0 8
b0 r
00
0-
b10011 f
b0 h
b0 g
b0 ;
b0 d
b0 m
b0 9
b0 c
b0 n
b0 <
b0 e
b0 @
b0 l
b100 >
b10100000000000010010011 3
b10100000000000010010011 7
b10100000000000010010011 !
b10100000000000010010011 ?
b10100000000000010010011 }
1D
b0 u
b0 $
b0 /
b0 z
b0 Z
b0 W
b0 ]
0q
b0 [
b0 _
0%
b0 I
b0 V
b0 \
b10011 1
b10011 S
b10011 b
b10011 k
b0 T
b100 =
b0 4
b0 "
b0 6
b0 |
b0 X
b0 '
b0 .
b0 y
b0 F
b0 K
b0 R
b0 a
b0 P
b0 `
b0 N
b0 o
b0 Q
b0 O
b0 J
b10011 2
b10011 L
b0 M
b100000 t
1(
#10000
0(
#15000
b100000 t
1(
#20000
0(
#25000
b100000 t
1(
#30000
0(
#35000
b100000 t
1(
#40000
0(
#45000
b101 9
b101 c
b101 n
b1 <
b1 e
b101 @
b101 l
b1000 >
b101000000000000100010011 3
b101000000000000100010011 7
b101000000000000100010011 !
b101000000000000100010011 ?
b101000000000000100010011 }
1q
b10100000000000010010011 1
b10100000000000010010011 S
b10100000000000010010011 b
b10100000000000010010011 k
b1000 =
b100 4
b100 "
b100 6
b100 |
b100 X
b10000000000000010000 J
0)
1(
#50000
0(
#55000
b101 5
b101 Y
b101 p
b101 E
b101 ^
b101 W
b101 ]
b101 I
b1010 9
b1010 c
b1010 n
b10 <
b10 e
b1010 @
b1010 l
b1100 >
b1000001000000110110011 3
b1000001000000110110011 7
b1000001000000110110011 !
b1000001000000110110011 ?
b1000001000000110110011 }
b101 '
b101 .
b101 y
b101 F
b101 K
b1 N
b1 o
b101 Q
b10100000000000010010011 2
b10100000000000010010011 L
b101000000000000100010011 1
b101000000000000100010011 S
b101000000000000100010011 b
b101000000000000100010011 k
b100 T
b1100 =
b1000 4
b1000 "
b1000 6
b1000 |
b1000 X
b1 *
1(
#60000
0(
#65000
b1010 5
b1010 Y
b1010 p
b10000 C
b10000 i
b101 :
b101 s
b1010 E
b1010 ^
b110011 f
b1 ;
b1 d
b1 m
b10 9
b10 c
b10 n
b11 <
b11 e
b10 @
b10 l
b10000 >
b1100000010000000100011 3
b1100000010000000100011 7
b1100000010000000100011 !
b1100000010000000100011 ?
b1100000010000000100011 }
b1010 W
b1010 ]
b1110 I
b1000001000000110110011 1
b1000001000000110110011 S
b1000001000000110110011 b
b1000001000000110110011 k
b1000 T
b10000 =
b1100 4
b1100 "
b1100 6
b1100 |
b1100 X
b1010 '
b1010 .
b1010 y
b1010 F
b1010 K
b10 N
b10 o
b1010 Q
b101000000000000100010011 2
b101000000000000100010011 L
b100 M
b10 *
1(
#70000
0(
#75000
b101 5
b101 Y
b101 p
b1 j
b101 E
b101 ^
b100010000000000101000000 C
b100010000000000101000000 i
b0 :
b0 s
0D
b0 W
b0 ]
b1010 I
b101 V
b101 \
b100011 f
b10 h
b0 ;
b0 d
b0 m
b11 9
b11 c
b11 n
b0 <
b0 e
b0 @
b0 l
b10100 >
b10001000000011 3
b10001000000011 7
b10001000000011 !
b10001000000011 ?
b10001000000011 }
b0 8
b0 r
b10 K
b111 '
b111 .
b111 y
b111 F
b101 P
b101 `
b11 N
b11 o
b10 Q
b1 O
b10000 J
b1000001000000110110011 2
b1000001000000110110011 L
b1000 M
b1100000010000000100011 1
b1100000010000000100011 S
b1100000010000000100011 b
b1100000010000000100011 k
b1100 T
b10100 =
b10000 4
b10000 "
b10000 6
b10000 |
b10000 X
b11 *
1(
#80000
0(
#85000
b0 j
b0 5
b0 Y
b0 p
b10000000001001010100 C
b10000000001001010100 i
b1111 #
b1111 A
b1111 {
b0 E
b0 ^
b11 f
b0 9
b0 c
b0 n
b100 <
b100 e
b0 @
b0 l
b11000 >
b10000011000001010110011 3
b10000011000001010110011 7
b10000011000001010110011 !
b10000011000001010110011 ?
b10000011000001010110011 }
1D
b1111 H
0q
b1100 I
b0 V
b0 \
b10001000000011 1
b10001000000011 S
b10001000000011 b
b10001000000011 k
b10000 T
b11000 =
b10100 4
b10100 "
b10100 6
b10100 |
b10100 X
b0 K
b0 '
b0 .
b0 y
b0 F
b0 P
b0 `
b0 N
b0 o
b11 Q
b0 O
b100010000000000101000000 J
b1100000010000000100011 2
b1100000010000000100011 L
b1100 M
b100 *
1(
#90000
0(
